pyhackgui/__init__.py
pyhackgui/core.py
pyhackgui-1.0.5.dist-info/licenses/LICENSE
pyhackgui-1.0.5.dist-info/METADATA
pyhackgui-1.0.5.dist-info/WHEEL
pyhackgui-1.0.5.dist-info/top_level.txt
pyhackgui-1.0.5.dist-info/RECORD
