Metadata-Version: 2.4
Name: pyhackgui
Version: 1.0.5
Summary: PyHackGUI - A Python GUI library for game overlay interfaces
Home-page: https://github.com/yourusername/pyhackgui
Author: LiangYu
Author-email: LiangYu <liangyu0611@gmail.com>
Maintainer-email: LiangYu <liangyu0611@gmail.com>
License: MIT
Project-URL: Homepage, https://github.com/yourusername/pyhackgui
Project-URL: Repository, https://github.com/yourusername/pyhackgui
Project-URL: Documentation, https://github.com/yourusername/pyhackgui/wiki
Project-URL: Bug Reports, https://github.com/yourusername/pyhackgui/issues
Keywords: gui,pygame,game,hack,overlay,transparent,window
Classifier: Development Status :: 4 - Beta
Classifier: Intended Audience :: Developers
Classifier: Topic :: Software Development :: Libraries :: Python Modules
Classifier: Topic :: Games/Entertainment
Classifier: License :: OSI Approved :: MIT License
Classifier: Programming Language :: Python :: 3
Classifier: Programming Language :: Python :: 3.7
Classifier: Programming Language :: Python :: 3.8
Classifier: Programming Language :: Python :: 3.9
Classifier: Programming Language :: Python :: 3.10
Classifier: Programming Language :: Python :: 3.11
Classifier: Operating System :: Microsoft :: Windows
Requires-Python: >=3.7
License-File: LICENSE
Requires-Dist: pygame>=2.0.0
Requires-Dist: pywin32>=227
Dynamic: author
Dynamic: home-page
Dynamic: license-file
Dynamic: requires-python
